tests/__init__.py
tests/test_drift_removal.py
tests/test_grids.py
tests/test_postprocessing.py
tests/test_preprocessing.py
tests/test_preprocessing_cloud.py
tests/test_regionmask.py
tests/test_utils.py
xmip/__init__.py
xmip/_version.py
xmip/drift_removal.py
xmip/grids.py
xmip/postprocessing.py
xmip/preprocessing.py
xmip/regionmask.py
xmip/utils.py
xmip/specs/staggered_grid_config.yaml
xmip-0.7.2.dist-info/LICENSE.txt
xmip-0.7.2.dist-info/METADATA
xmip-0.7.2.dist-info/WHEEL
xmip-0.7.2.dist-info/top_level.txt
xmip-0.7.2.dist-info/RECORD
